{"box_data": [{"position": {"minX": 166.25, "minY": 146.875, "maxX": 216.0, "maxY": 199.375}, "class_id": 0, "box_caption": "vehicle 0.832", "scores": {"class_score": 0.83154296875}, "domain": "pixel"}, {"position": {"minX": 320.25, "minY": 154.25, "maxX": 374.75, "maxY": 189.0}, "class_id": 0, "box_caption": "vehicle 0.742", "scores": {"class_score": 0.74169921875}, "domain": "pixel"}, {"position": {"minX": 46.0625, "minY": 44.34375, "maxX": 87.6875, "maxY": 70.25}, "class_id": 0, "box_caption": "vehicle 0.167", "scores": {"class_score": 0.166748046875}, "domain": "pixel"}, {"position": {"minX": 48.9375, "minY": 50.09375, "maxX": 90.5625, "maxY": 67.375}, "class_id": 0, "box_caption": "vehicle 0.092", "scores": {"class_score": 0.09246826171875}, "domain": "pixel"}, {"position": {"minX": 67.0, "minY": 51.0, "maxX": 99.875, "maxY": 71.1875}, "class_id": 0, "box_caption": "vehicle 0.039", "scores": {"class_score": 0.039459228515625}, "domain": "pixel"}, {"position": {"minX": 319.25, "minY": 144.0, "maxX": 389.25, "maxY": 204.5}, "class_id": 0, "box_caption": "vehicle 0.032", "scores": {"class_score": 0.031951904296875}, "domain": "pixel"}, {"position": {"minX": 304.75, "minY": 130.75, "maxX": 377.75, "maxY": 195.25}, "class_id": 0, "box_caption": "vehicle 0.023", "scores": {"class_score": 0.0226898193359375}, "domain": "pixel"}, {"position": {"minX": 69.0, "minY": 55.09375, "maxX": 98.875, "maxY": 67.75}, "class_id": 0, "box_caption": "vehicle 0.019", "scores": {"class_score": 0.0189056396484375}, "domain": "pixel"}, {"position": {"minX": 45.40625, "minY": 34.75, "maxX": 95.125, "maxY": 75.1875}, "class_id": 0, "box_caption": "vehicle 0.018", "scores": {"class_score": 0.0181121826171875}, "domain": "pixel"}, {"position": {"minX": 75.125, "minY": 53.53125, "maxX": 102.625, "maxY": 69.25}, "class_id": 0, "box_caption": "vehicle 0.011", "scores": {"class_score": 0.0110015869140625}, "domain": "pixel"}, {"position": {"minX": 41.6875, "minY": 38.34375, "maxX": 79.5, "maxY": 65.25}, "class_id": 0, "box_caption": "vehicle 0.009", "scores": {"class_score": 0.00927734375}, "domain": "pixel"}, {"position": {"minX": 113.1875, "minY": 74.75, "maxX": 304.0, "maxY": 268.5}, "class_id": 0, "box_caption": "vehicle 0.008", "scores": {"class_score": 0.007656097412109375}, "domain": "pixel"}, {"position": {"minX": 79.1875, "minY": 57.5625, "maxX": 99.4375, "maxY": 66.875}, "class_id": 0, "box_caption": "vehicle 0.007", "scores": {"class_score": 0.00688934326171875}, "domain": "pixel"}, {"position": {"minX": 377.25, "minY": 236.75, "maxX": 394.75, "maxY": 286.25}, "class_id": 0, "box_caption": "vehicle 0.007", "scores": {"class_score": 0.006877899169921875}, "domain": "pixel"}, {"position": {"minX": 416.5, "minY": 256.5, "maxX": 435.0, "maxY": 271.0}, "class_id": 0, "box_caption": "vehicle 0.007", "scores": {"class_score": 0.00652313232421875}, "domain": "pixel"}, {"position": {"minX": 190.25, "minY": 53.3125, "maxX": 479.25, "maxY": 296.25}, "class_id": 0, "box_caption": "vehicle 0.006", "scores": {"class_score": 0.005725860595703125}, "domain": "pixel"}, {"position": {"minX": 54.15625, "minY": 29.75, "maxX": 88.125, "maxY": 67.1875}, "class_id": 0, "box_caption": "vehicle 0.006", "scores": {"class_score": 0.00568389892578125}, "domain": "pixel"}, {"position": {"minX": 395.75, "minY": 246.375, "maxX": 411.25, "maxY": 273.75}, "class_id": 0, "box_caption": "vehicle 0.006", "scores": {"class_score": 0.00560760498046875}, "domain": "pixel"}, {"position": {"minX": 383.0, "minY": 242.125, "maxX": 396.5, "maxY": 269.75}, "class_id": 0, "box_caption": "vehicle 0.005", "scores": {"class_score": 0.004665374755859375}, "domain": "pixel"}, {"position": {"minX": 380.5, "minY": 245.625, "maxX": 391.5, "maxY": 269.75}, "class_id": 0, "box_caption": "vehicle 0.005", "scores": {"class_score": 0.00466156005859375}, "domain": "pixel"}, {"position": {"minX": 372.5, "minY": 233.375, "maxX": 412.5, "maxY": 279.5}, "class_id": 0, "box_caption": "vehicle 0.005", "scores": {"class_score": 0.004650115966796875}, "domain": "pixel"}, {"position": {"minX": 403.75, "minY": 253.75, "maxX": 434.25, "maxY": 276.75}, "class_id": 0, "box_caption": "vehicle 0.005", "scores": {"class_score": 0.004650115966796875}, "domain": "pixel"}, {"position": {"minX": 408.0, "minY": 259.0, "maxX": 432.5, "maxY": 269.5}, "class_id": 0, "box_caption": "vehicle 0.004", "scores": {"class_score": 0.0044708251953125}, "domain": "pixel"}, {"position": {"minX": 79.5, "minY": 99.75, "maxX": 266.0, "maxY": 210.0}, "class_id": 0, "box_caption": "vehicle 0.004", "scores": {"class_score": 0.004413604736328125}, "domain": "pixel"}, {"position": {"minX": 46.78125, "minY": 50.8125, "maxX": 76.0, "maxY": 74.375}, "class_id": 0, "box_caption": "vehicle 0.004", "scores": {"class_score": 0.004215240478515625}, "domain": "pixel"}, {"position": {"minX": 56.6875, "minY": 53.8125, "maxX": 80.4375, "maxY": 69.1875}, "class_id": 0, "box_caption": "vehicle 0.004", "scores": {"class_score": 0.0037174224853515625}, "domain": "pixel"}, {"position": {"minX": 230.0, "minY": 40.9375, "maxX": 436.5, "maxY": 244.25}, "class_id": 0, "box_caption": "vehicle 0.004", "scores": {"class_score": 0.003635406494140625}, "domain": "pixel"}, {"position": {"minX": 374.25, "minY": 241.375, "maxX": 395.25, "maxY": 272.25}, "class_id": 0, "box_caption": "vehicle 0.003", "scores": {"class_score": 0.00293731689453125}, "domain": "pixel"}, {"position": {"minX": 42.25, "minY": 53.46875, "maxX": 81.3125, "maxY": 70.375}, "class_id": 0, "box_caption": "vehicle 0.003", "scores": {"class_score": 0.0029048919677734375}, "domain": "pixel"}, {"position": {"minX": 373.0, "minY": 250.875, "maxX": 390.0, "maxY": 263.5}, "class_id": 0, "box_caption": "vehicle 0.003", "scores": {"class_score": 0.0028839111328125}, "domain": "pixel"}, {"position": {"minX": 372.0, "minY": 251.0, "maxX": 387.0, "maxY": 274.0}, "class_id": 0, "box_caption": "vehicle 0.003", "scores": {"class_score": 0.0026950836181640625}, "domain": "pixel"}, {"position": {"minX": 373.0, "minY": 241.625, "maxX": 387.5, "maxY": 268.0}, "class_id": 0, "box_caption": "vehicle 0.002", "scores": {"class_score": 0.0024280548095703125}, "domain": "pixel"}, {"position": {"minX": 62.4375, "minY": 52.28125, "maxX": 88.3125, "maxY": 70.75}, "class_id": 0, "box_caption": "vehicle 0.002", "scores": {"class_score": 0.00241851806640625}, "domain": "pixel"}, {"position": {"minX": 375.0, "minY": 223.75, "maxX": 412.0, "maxY": 299.75}, "class_id": 0, "box_caption": "vehicle 0.002", "scores": {"class_score": 0.0024089813232421875}, "domain": "pixel"}, {"position": {"minX": 59.0625, "minY": 45.59375, "maxX": 97.8125, "maxY": 71.0}, "class_id": 0, "box_caption": "vehicle 0.002", "scores": {"class_score": 0.0023860931396484375}, "domain": "pixel"}, {"position": {"minX": 113.125, "minY": 246.125, "maxX": 191.125, "maxY": 276.25}, "class_id": 0, "box_caption": "vehicle 0.002", "scores": {"class_score": 0.0023555755615234375}, "domain": "pixel"}, {"position": {"minX": 392.5, "minY": 244.0, "maxX": 408.5, "maxY": 268.0}, "class_id": 0, "box_caption": "vehicle 0.002", "scores": {"class_score": 0.002277374267578125}, "domain": "pixel"}, {"position": {"minX": 387.75, "minY": 253.5, "maxX": 408.75, "maxY": 277.0}, "class_id": 0, "box_caption": "vehicle 0.002", "scores": {"class_score": 0.0022525787353515625}, "domain": "pixel"}, {"position": {"minX": 374.25, "minY": 227.125, "maxX": 399.25, "maxY": 278.25}, "class_id": 0, "box_caption": "vehicle 0.002", "scores": {"class_score": 0.002231597900390625}, "domain": "pixel"}, {"position": {"minX": 386.25, "minY": 237.75, "maxX": 416.75, "maxY": 277.75}, "class_id": 0, "box_caption": "vehicle 0.002", "scores": {"class_score": 0.0021915435791015625}, "domain": "pixel"}, {"position": {"minX": 453.5, "minY": 251.75, "maxX": 471.5, "maxY": 281.25}, "class_id": 0, "box_caption": "vehicle 0.002", "scores": {"class_score": 0.002185821533203125}, "domain": "pixel"}, {"position": {"minX": 368.5, "minY": 244.0, "maxX": 404.5, "maxY": 275.5}, "class_id": 0, "box_caption": "vehicle 0.002", "scores": {"class_score": 0.002109527587890625}, "domain": "pixel"}, {"position": {"minX": 385.0, "minY": 251.125, "maxX": 411.5, "maxY": 266.0}, "class_id": 0, "box_caption": "vehicle 0.002", "scores": {"class_score": 0.0020885467529296875}, "domain": "pixel"}, {"position": {"minX": 424.0, "minY": 250.875, "maxX": 438.0, "maxY": 271.0}, "class_id": 0, "box_caption": "vehicle 0.002", "scores": {"class_score": 0.002086639404296875}, "domain": "pixel"}, {"position": {"minX": 123.375, "minY": 234.75, "maxX": 186.875, "maxY": 285.25}, "class_id": 0, "box_caption": "vehicle 0.002", "scores": {"class_score": 0.002071380615234375}, "domain": "pixel"}, {"position": {"minX": 34.125, "minY": 16.53125, "maxX": 97.125, "maxY": 82.625}, "class_id": 0, "box_caption": "vehicle 0.002", "scores": {"class_score": 0.0020294189453125}, "domain": "pixel"}, {"position": {"minX": 422.0, "minY": 255.625, "maxX": 439.0, "maxY": 275.0}, "class_id": 0, "box_caption": "vehicle 0.002", "scores": {"class_score": 0.00200653076171875}, "domain": "pixel"}, {"position": {"minX": 377.0, "minY": 244.75, "maxX": 392.5, "maxY": 263.25}, "class_id": 0, "box_caption": "vehicle 0.002", "scores": {"class_score": 0.001880645751953125}, "domain": "pixel"}, {"position": {"minX": 271.75, "minY": 262.5, "maxX": 285.75, "maxY": 273.5}, "class_id": 0, "box_caption": "vehicle 0.002", "scores": {"class_score": 0.0018625259399414062}, "domain": "pixel"}, {"position": {"minX": 235.75, "minY": 105.625, "maxX": 250.5, "maxY": 117.875}, "class_id": 0, "box_caption": "vehicle 0.002", "scores": {"class_score": 0.0018520355224609375}, "domain": "pixel"}, {"position": {"minX": 339.5, "minY": 234.625, "maxX": 362.0, "maxY": 275.0}, "class_id": 0, "box_caption": "vehicle 0.002", "scores": {"class_score": 0.0018281936645507812}, "domain": "pixel"}, {"position": {"minX": 374.5, "minY": 242.0, "maxX": 391.0, "maxY": 259.5}, "class_id": 0, "box_caption": "vehicle 0.002", "scores": {"class_score": 0.0018262863159179688}, "domain": "pixel"}, {"position": {"minX": 48.4375, "minY": 73.75, "maxX": 88.6875, "maxY": 147.0}, "class_id": 0, "box_caption": "vehicle 0.002", "scores": {"class_score": 0.001781463623046875}, "domain": "pixel"}, {"position": {"minX": 167.5, "minY": 155.875, "maxX": 204.25, "maxY": 203.375}, "class_id": 0, "box_caption": "vehicle 0.002", "scores": {"class_score": 0.0017213821411132812}, "domain": "pixel"}, {"position": {"minX": 148.75, "minY": 7.9375, "maxX": 230.75, "maxY": 115.5625}, "class_id": 0, "box_caption": "vehicle 0.002", "scores": {"class_score": 0.0016622543334960938}, "domain": "pixel"}, {"position": {"minX": 460.5, "minY": 254.75, "maxX": 481.5, "maxY": 279.25}, "class_id": 0, "box_caption": "vehicle 0.002", "scores": {"class_score": 0.0016603469848632812}, "domain": "pixel"}, {"position": {"minX": 413.25, "minY": 257.0, "maxX": 431.75, "maxY": 276.0}, "class_id": 0, "box_caption": "vehicle 0.002", "scores": {"class_score": 0.0015583038330078125}, "domain": "pixel"}, {"position": {"minX": 157.0, "minY": 5.21875, "maxX": 206.5, "maxY": 98.25}, "class_id": 0, "box_caption": "vehicle 0.002", "scores": {"class_score": 0.0015392303466796875}, "domain": "pixel"}, {"position": {"minX": 298.75, "minY": 150.25, "maxX": 364.25, "maxY": 198.25}, "class_id": 0, "box_caption": "vehicle 0.002", "scores": {"class_score": 0.0015363693237304688}, "domain": "pixel"}, {"position": {"minX": 22.125, "minY": 140.0, "maxX": 125.25, "maxY": 277.75}, "class_id": 0, "box_caption": "vehicle 0.002", "scores": {"class_score": 0.00151824951171875}, "domain": "pixel"}, {"position": {"minX": 450.75, "minY": 258.5, "maxX": 474.25, "maxY": 270.5}, "class_id": 0, "box_caption": "vehicle 0.002", "scores": {"class_score": 0.0015153884887695312}, "domain": "pixel"}, {"position": {"minX": 33.875, "minY": 83.5625, "maxX": 67.375, "maxY": 140.25}, "class_id": 0, "box_caption": "vehicle 0.002", "scores": {"class_score": 0.0015134811401367188}, "domain": "pixel"}, {"position": {"minX": 370.0, "minY": 245.75, "maxX": 415.5, "maxY": 269.75}, "class_id": 0, "box_caption": "vehicle 0.001", "scores": {"class_score": 0.0014886856079101562}, "domain": "pixel"}, {"position": {"minX": 45.8125, "minY": 50.96875, "maxX": 68.9375, "maxY": 70.0}, "class_id": 0, "box_caption": "vehicle 0.001", "scores": {"class_score": 0.0014848709106445312}, "domain": "pixel"}, {"position": {"minX": 413.0, "minY": 256.5, "maxX": 432.0, "maxY": 266.0}, "class_id": 0, "box_caption": "vehicle 0.001", "scores": {"class_score": 0.001415252685546875}, "domain": "pixel"}, {"position": {"minX": 42.9375, "minY": 75.125, "maxX": 58.1875, "maxY": 143.875}, "class_id": 0, "box_caption": "vehicle 0.001", "scores": {"class_score": 0.0013589859008789062}, "domain": "pixel"}, {"position": {"minX": 411.0, "minY": 239.5, "maxX": 440.5, "maxY": 278.0}, "class_id": 0, "box_caption": "vehicle 0.001", "scores": {"class_score": 0.001346588134765625}, "domain": "pixel"}, {"position": {"minX": 345.5, "minY": 4.6875, "maxX": 455.5, "maxY": 130.5}, "class_id": 0, "box_caption": "vehicle 0.001", "scores": {"class_score": 0.0013303756713867188}, "domain": "pixel"}, {"position": {"minX": 171.5, "minY": 21.6875, "maxX": 215.0, "maxY": 97.0625}, "class_id": 0, "box_caption": "vehicle 0.001", "scores": {"class_score": 0.0013017654418945312}, "domain": "pixel"}, {"position": {"minX": 136.625, "minY": 231.25, "maxX": 172.375, "maxY": 280.25}, "class_id": 0, "box_caption": "vehicle 0.001", "scores": {"class_score": 0.0012636184692382812}, "domain": "pixel"}, {"position": {"minX": 27.453125, "minY": 92.0625, "maxX": 76.6875, "maxY": 129.0}, "class_id": 0, "box_caption": "vehicle 0.001", "scores": {"class_score": 0.0012636184692382812}, "domain": "pixel"}, {"position": {"minX": 35.0625, "minY": 87.25, "maxX": 56.9375, "maxY": 150.875}, "class_id": 0, "box_caption": "vehicle 0.001", "scores": {"class_score": 0.0012264251708984375}, "domain": "pixel"}, {"position": {"minX": 43.0625, "minY": 138.5, "maxX": 90.1875, "maxY": 226.5}, "class_id": 0, "box_caption": "vehicle 0.001", "scores": {"class_score": 0.0012264251708984375}, "domain": "pixel"}, {"position": {"minX": 379.0, "minY": 247.0, "maxX": 407.0, "maxY": 267.5}, "class_id": 0, "box_caption": "vehicle 0.001", "scores": {"class_score": 0.0012159347534179688}, "domain": "pixel"}, {"position": {"minX": 449.75, "minY": 120.1875, "maxX": 521.0, "maxY": 198.0}, "class_id": 0, "box_caption": "vehicle 0.001", "scores": {"class_score": 0.0012102127075195312}, "domain": "pixel"}, {"position": {"minX": 39.34375, "minY": 24.65625, "maxX": 111.375, "maxY": 103.25}, "class_id": 0, "box_caption": "vehicle 0.001", "scores": {"class_score": 0.0012102127075195312}, "domain": "pixel"}, {"position": {"minX": 383.25, "minY": 246.0, "maxX": 421.75, "maxY": 271.5}, "class_id": 0, "box_caption": "vehicle 0.001", "scores": {"class_score": 0.0012035369873046875}, "domain": "pixel"}, {"position": {"minX": 369.0, "minY": 248.5, "maxX": 394.0, "maxY": 276.5}, "class_id": 0, "box_caption": "vehicle 0.001", "scores": {"class_score": 0.0012006759643554688}, "domain": "pixel"}, {"position": {"minX": 44.21875, "minY": 93.5, "maxX": 60.34375, "maxY": 134.125}, "class_id": 0, "box_caption": "vehicle 0.001", "scores": {"class_score": 0.0011873245239257812}, "domain": "pixel"}, {"position": {"minX": 341.75, "minY": 246.875, "maxX": 356.25, "maxY": 280.75}, "class_id": 0, "box_caption": "vehicle 0.001", "scores": {"class_score": 0.0011739730834960938}, "domain": "pixel"}, {"position": {"minX": 393.0, "minY": 48.375, "maxX": 592.5, "maxY": 221.125}, "class_id": 0, "box_caption": "vehicle 0.001", "scores": {"class_score": 0.0011701583862304688}, "domain": "pixel"}, {"position": {"minX": 149.375, "minY": 27.65625, "maxX": 242.125, "maxY": 92.75}, "class_id": 0, "box_caption": "vehicle 0.001", "scores": {"class_score": 0.0011615753173828125}, "domain": "pixel"}, {"position": {"minX": 308.25, "minY": 4.09375, "maxX": 433.25, "maxY": 71.25}, "class_id": 0, "box_caption": "vehicle 0.001", "scores": {"class_score": 0.0011320114135742188}, "domain": "pixel"}, {"position": {"minX": 180.875, "minY": 249.25, "maxX": 226.125, "maxY": 267.75}, "class_id": 0, "box_caption": "vehicle 0.001", "scores": {"class_score": 0.0011310577392578125}, "domain": "pixel"}, {"position": {"minX": 362.0, "minY": 243.25, "maxX": 433.5, "maxY": 278.25}, "class_id": 0, "box_caption": "vehicle 0.001", "scores": {"class_score": 0.001129150390625}, "domain": "pixel"}, {"position": {"minX": 496.0, "minY": 2.78125, "maxX": 539.0, "maxY": 91.125}, "class_id": 0, "box_caption": "vehicle 0.001", "scores": {"class_score": 0.0011129379272460938}, "domain": "pixel"}, {"position": {"minX": 7.28125, "minY": 127.625, "maxX": 104.375, "maxY": 235.625}, "class_id": 0, "box_caption": "vehicle 0.001", "scores": {"class_score": 0.0011110305786132812}, "domain": "pixel"}, {"position": {"minX": 43.125, "minY": 121.5, "maxX": 99.625, "maxY": 182.0}, "class_id": 0, "box_caption": "vehicle 0.001", "scores": {"class_score": 0.0011091232299804688}, "domain": "pixel"}, {"position": {"minX": 270.25, "minY": 265.5, "maxX": 284.25, "maxY": 275.5}, "class_id": 0, "box_caption": "vehicle 0.001", "scores": {"class_score": 0.0010967254638671875}, "domain": "pixel"}, {"position": {"minX": 103.25, "minY": 253.5, "maxX": 173.25, "maxY": 269.0}, "class_id": 0, "box_caption": "vehicle 0.001", "scores": {"class_score": 0.0010957717895507812}, "domain": "pixel"}, {"position": {"minX": 324.0, "minY": 156.5, "maxX": 378.5, "maxY": 179.75}, "class_id": 0, "box_caption": "vehicle 0.001", "scores": {"class_score": 0.0010957717895507812}, "domain": "pixel"}, {"position": {"minX": 447.75, "minY": 229.5, "maxX": 489.25, "maxY": 310.5}, "class_id": 0, "box_caption": "vehicle 0.001", "scores": {"class_score": 0.001094818115234375}, "domain": "pixel"}, {"position": {"minX": 414.25, "minY": 262.75, "maxX": 430.75, "maxY": 279.75}, "class_id": 0, "box_caption": "vehicle 0.001", "scores": {"class_score": 0.0010805130004882812}, "domain": "pixel"}, {"position": {"minX": 33.28125, "minY": 125.0625, "maxX": 63.71875, "maxY": 139.75}, "class_id": 0, "box_caption": "vehicle 0.001", "scores": {"class_score": 0.001071929931640625}, "domain": "pixel"}, {"position": {"minX": 370.75, "minY": 13.125, "maxX": 406.75, "maxY": 143.0}, "class_id": 0, "box_caption": "vehicle 0.001", "scores": {"class_score": 0.0010614395141601562}, "domain": "pixel"}, {"position": {"minX": 332.25, "minY": -7.5, "maxX": 378.75, "maxY": 101.75}, "class_id": 0, "box_caption": "vehicle 0.001", "scores": {"class_score": 0.0010585784912109375}, "domain": "pixel"}, {"position": {"minX": 303.25, "minY": 150.25, "maxX": 379.75, "maxY": 180.25}, "class_id": 0, "box_caption": "vehicle 0.001", "scores": {"class_score": 0.0010576248168945312}, "domain": "pixel"}, {"position": {"minX": 596.0, "minY": 214.625, "maxX": 636.0, "maxY": 312.5}, "class_id": 0, "box_caption": "vehicle 0.001", "scores": {"class_score": 0.0010385513305664062}, "domain": "pixel"}, {"position": {"minX": 261.75, "minY": -52.0, "maxX": 531.0, "maxY": 210.75}, "class_id": 0, "box_caption": "vehicle 0.001", "scores": {"class_score": 0.0010318756103515625}, "domain": "pixel"}, {"position": {"minX": 37.25, "minY": 99.3125, "maxX": 59.5, "maxY": 135.625}, "class_id": 0, "box_caption": "vehicle 0.001", "scores": {"class_score": 0.0010309219360351562}, "domain": "pixel"}, {"position": {"minX": 359.75, "minY": 228.0, "maxX": 388.25, "maxY": 306.0}, "class_id": 0, "box_caption": "vehicle 0.001", "scores": {"class_score": 0.0010232925415039062}, "domain": "pixel"}, {"position": {"minX": 40.28125, "minY": 54.53125, "maxX": 113.75, "maxY": 150.25}, "class_id": 0, "box_caption": "vehicle 0.001", "scores": {"class_score": 0.0010175704956054688}, "domain": "pixel"}, {"position": {"minX": -13.96875, "minY": 235.125, "maxX": 87.75, "maxY": 288.75}, "class_id": 0, "box_caption": "vehicle 0.001", "scores": {"class_score": 0.001007080078125}, "domain": "pixel"}], "class_labels": {"0": "vehicle"}}